control_f/__init__.py
control_f/api.py
ctrlf/__init__.py
ctrlf/api.py
control_f-0.1.5.dist-info/LICENSE
control_f-0.1.5.dist-info/METADATA
control_f-0.1.5.dist-info/WHEEL
control_f-0.1.5.dist-info/top_level.txt
control_f-0.1.5.dist-info/RECORD
