Metadata-Version: 2.1
Name: control-f
Version: 0.1.5
Summary: Control-F Python client
Home-page: https://github.com/gduverger/control-f-client
Author: Georges Duverger
Author-email: georges.duverger@gmail.com
License: MIT
Platform: UNKNOWN
Classifier: Programming Language :: Python :: 3
Classifier: License :: OSI Approved :: MIT License
Classifier: Operating System :: OS Independent
Classifier: Intended Audience :: Developers
Classifier: Natural Language :: English
Requires-Python: >=3
